dojot_toolbox-0.0.2.data/scripts/dojot
lib/__init__.py
lib/ansible_cli.py
lib/auth.py
lib/authenticable.py
lib/component.py
lib/constants.py
lib/cron.py
lib/device_manager.py
lib/dojot_cli.py
lib/gui.py
lib/iotagent_lwm2m.py
lib/iotagent_mqtt.py
lib/k8s_cli.py
lib/kafka.py
lib/kong.py
lib/main.py
lib/mongodb.py
lib/optional.py
lib/persistent.py
lib/persister.py
lib/postgres.py
lib/quantifiable.py
lib/repository.py
lib/scalable.py
lib/spinner_progress.py
test/__init__.py
test/auth_test.py
test/authenticable_test.py
test/cron_test.py
test/dojot_cli_test.py
test/gui_test.py
test/iotagent_lwm2m_test.py
test/iotagent_mqtt_test.py
test/k8s_cli_test.py
test/kafka_test.py
test/kong_test.py
test/mongodb_test.py
test/optional_test.py
test/persistent_test.py
test/persister_test.py
test/postgres_test.py
test/repository_test.py
test/scalable_test.py
test/suite_test.py
dojot_toolbox-0.0.2.dist-info/LICENCE
dojot_toolbox-0.0.2.dist-info/METADATA
dojot_toolbox-0.0.2.dist-info/WHEEL
dojot_toolbox-0.0.2.dist-info/top_level.txt
dojot_toolbox-0.0.2.dist-info/RECORD
